CLASSIFIERS
HISTORY.rst
LICENSE.txt
MANIFEST.in
README.rst
requirements.txt
setup.cfg
setup.py
versioneer.py
wsh/__init__.py
wsh/_version.py
wsh/app.py
wsh/command_processor.py
wsh/connection.py
wsh/interface.py
wsh/key_bindings.py
wsh/style.py
wsh/version.py
wsh/wsh.py
wsh.egg-info/PKG-INFO
wsh.egg-info/SOURCES.txt
wsh.egg-info/dependency_links.txt
wsh.egg-info/entry_points.txt
wsh.egg-info/not-zip-safe
wsh.egg-info/requires.txt
wsh.egg-info/top_level.txt