Metadata-Version: 1.1
Name: wsh
Version: 0.2.2
Summary: An interactive WebSocket shell
Home-page: https://wsh.readthedocs.org
Author: Pinn Technologies, Inc.
Author-email: developers@pinn.ai
License: MIT
Platform: UNKNOWN
Classifier: Development Status :: 2 - Pre-Alpha
Classifier: Intended Audience :: Developers
Classifier: License :: OSI Approved :: MIT License
Classifier: Topic :: Software Development :: Libraries :: Python Modules
Classifier: Programming Language :: Python :: 3.4
Classifier: Programming Language :: Python :: 3.5
Classifier: Programming Language :: Python :: 3.6
Classifier: Programming Language :: Python :: 3.7
Classifier: Programming Language :: Python :: Implementation :: PyPy
